extprint/__init__.py
extprint/exceptions.py
extprint/extprint.py
extprint-0.1.0.dist-info/LICENSE
extprint-0.1.0.dist-info/METADATA
extprint-0.1.0.dist-info/WHEEL
extprint-0.1.0.dist-info/top_level.txt
extprint-0.1.0.dist-info/RECORD
