Metadata-Version: 2.1
Name: extprint
Version: 0.1.0
Summary: extended print
Home-page: https://github.com/cccaaannn/extprint
Author: Can Kurt
Author-email: can.kurt.aa@gmail.com
License: UNKNOWN
Platform: UNKNOWN
Classifier: Programming Language :: Python :: 3
Classifier: License :: OSI Approved :: MIT License
Classifier: Operating System :: OS Independent
